happy_utils/__init__.py
happy_utils/happy_utils.py
happy_utils-0.1.3.dist-info/METADATA
happy_utils-0.1.3.dist-info/WHEEL
happy_utils-0.1.3.dist-info/RECORD
